.gitignore
editdistance/__init__.pxd
editdistance/__init__.py
editdistance/_editdistance.cpp
editdistance/_editdistance.h
editdistance/bycython.cpp
editdistance/bycython.cpython-38-aarch64-linux-gnu.so
editdistance/bycython.pxd
editdistance/bycython.pyx
editdistance/def.h
ilt_editdistance-0.8.2.dist-info/METADATA
ilt_editdistance-0.8.2.dist-info/WHEEL
ilt_editdistance-0.8.2.dist-info/entry_points.txt
ilt_editdistance-0.8.2.dist-info/RECORD
ilt_editdistance-0.8.2.dist-info/licenses/LICENSE
