Metadata-Version: 2.1
Name: ilt-editdistance
Version: 0.8.2
Summary: Fast implementation of the edit distance (Levenshtein distance)
Author-Email: Hiroyuki Tanaka <aflc0x@gmail.com>
Maintainer-Email: Eric Joanis <Eric.Joanis@nrc-cnrc.gc.ca>
License: MIT
Project-URL: Homepage, https://github.com/nrc-ilt/editdistance
Project-URL: Documentation, https://github.com/nrc-ilt/editdistance
Project-URL: Repository, https://github.com/nrc-ilt/editdistance
Requires-Python: >=3.8
